flow_claude/__init__.py
flow_claude/post_hook_handler.py
flow_claude/test_launch_worker.py
flow_claude/commands/__init__.py
flow_claude/commands/flow_cli.py
flow_claude/commands/set_parallel.py
flow_claude/commands/toggle_auto.py
flow_claude/core/__init__.py
flow_claude/scripts/__init__.py
flow_claude/scripts/create_plan_branch.py
flow_claude/scripts/create_task_branch.py
flow_claude/scripts/launch_worker.py
flow_claude/scripts/parse_branch_latest_commit.py
flow_claude/scripts/read_plan_metadata.py
flow_claude/scripts/read_task_metadata.py
flow_claude/scripts/stop_hook_handler.py
flow_claude/scripts/update_plan_branch.py
flow_claude/setup_ui/__init__.py
flow_claude/setup_ui/app.py
flow_claude/setup_ui/claude_generator.py
flow_claude/setup_ui/git_utils.py
flow_claude/setup_ui/screens.py
flow_claude/templates/settings.local.json
flow_claude/templates/agents/user.md
flow_claude/templates/agents/worker-template.md
flow_claude/templates/commands/auto.md
flow_claude/templates/commands/parallel.md
flow_claude/templates/skills/git-tools/SKILL.md
flow_claude/templates/skills/launch-workers/SKILL.md
flow_claude/templates/skills/your-workflow/SKILL.md
flow_claude/utils/__init__.py
flow_claude/utils/mcp_loader.py
flow_claude-1.0.1.dist-info/licenses/LICENSE
flow_claude-1.0.1.dist-info/METADATA
flow_claude-1.0.1.dist-info/WHEEL
flow_claude-1.0.1.dist-info/entry_points.txt
flow_claude-1.0.1.dist-info/top_level.txt
flow_claude-1.0.1.dist-info/RECORD
