Metadata-Version: 2.4
Name: flow-claude
Version: 1.0.1
Summary: Claude Code UI-native autonomous development system with git-first architecture
Author: Flow-Claude Contributors
License: MIT
Project-URL: Homepage, https://github.com/a5507203/flow-claude
Project-URL: Repository, https://github.com/a5507203/flow-claude
Project-URL: Issues, https://github.com/a5507203/flow-claude/issues
Requires-Python: >=3.10
License-File: LICENSE
Requires-Dist: claude-agent-sdk>=0.1.0
Requires-Dist: click>=8.1.0
Requires-Dist: textual>=0.40.0
Requires-Dist: psutil>=7.1.3
Provides-Extra: dev
Requires-Dist: pytest>=7.0.0; extra == "dev"
Requires-Dist: pytest-asyncio>=0.21.0; extra == "dev"
Requires-Dist: ruff>=0.1.0; extra == "dev"
Dynamic: license-file
